src/BinomialDistribution.py
src/Distributions.py
src/ExponentialDistribution.py
src/GeometricDistribution.py
src/HypergeometricDistribution.py
src/NormalDistribution.py
src/PoissonDistribution.py
src/RectangularDistribution.py
src/SymmetricTriangularDistribution.py
src/TriangularDistribution.py
src/__init__.py
StatsPyDistribution-0.0.5.dist-info/LICENSE
StatsPyDistribution-0.0.5.dist-info/METADATA
StatsPyDistribution-0.0.5.dist-info/WHEEL
StatsPyDistribution-0.0.5.dist-info/top_level.txt
StatsPyDistribution-0.0.5.dist-info/RECORD
