Metadata-Version: 2.1
Name: StatsPyDistribution
Version: 0.0.5
Summary: Statistics probability distribution
Home-page: https://github.com/sbkshetry/StatsPyDistribution
Author: Shankar Kshetry
Author-email: sbkshetry@gmail.com
License: UNKNOWN
Platform: UNKNOWN
Classifier: Programming Language :: Python :: 3
Classifier: License :: OSI Approved :: Apache Software License
Classifier: Operating System :: OS Independent
License-File: LICENSE
